tethys_wrf/__init__.py
tethys_wrf/gis.py
tethys_wrf/main.py
tethys_wrf/sio.py
tethys_wrf/utils.py
tethys_wrf/virtual_parameters.py
tethys_wrf/wrftools.py
tethys_wrf/tests/__init__.py
tethys_wrf/tests/utest_wrf.py
tethys_wrf/tests/working.py
tethys_wrf-0.4.19.dist-info/LICENSE
tethys_wrf-0.4.19.dist-info/METADATA
tethys_wrf-0.4.19.dist-info/WHEEL
tethys_wrf-0.4.19.dist-info/top_level.txt
tethys_wrf-0.4.19.dist-info/RECORD
