Metadata-Version: 2.1
Name: tethys-wrf
Version: 0.4.19
Summary: tethys wrf utilities
Home-page: https://github.com/mullenkamp/tethys-wrf
Author: Mike Kittridge
Author-email: mullenkamp1@gmail.com
License: Apache
Keywords: tethys wrf
Classifier: Development Status :: 3 - Alpha
Classifier: Intended Audience :: Developers
Classifier: Topic :: Software Development :: Build Tools
Classifier: License :: OSI Approved :: Apache Software License
Classifier: Programming Language :: Python :: 2
Classifier: Programming Language :: Python :: 2.7
Classifier: Programming Language :: Python :: 3
Classifier: Programming Language :: Python :: 3.4
Classifier: Programming Language :: Python :: 3.5
Classifier: Programming Language :: Python :: 3.6
License-File: LICENSE
Requires-Dist: dask
Requires-Dist: pyproj
Requires-Dist: netcdf4
Requires-Dist: toolz
Requires-Dist: wrf-python
Requires-Dist: tethys-utils (==0.7.35)
